aizen/__init__.py
aizen-0.0.0.dist-info/METADATA
aizen-0.0.0.dist-info/WHEEL
aizen-0.0.0.dist-info/RECORD
