Metadata-Version: 2.1
Name: aizen
Version: 0.0.0
Summary: AI execution engine
Author: Harsh Verma
Author-email: synacktra.work@gmail.com
Requires-Python: >=3.8,<4.0
Classifier: Programming Language :: Python :: 3
Classifier: Programming Language :: Python :: 3.8
Classifier: Programming Language :: Python :: 3.9
Classifier: Programming Language :: Python :: 3.10
Classifier: Programming Language :: Python :: 3.11
Classifier: Programming Language :: Python :: 3.12
